LICENSE
MANIFEST.in
README.rst
pyproject.toml
setup.py
clickhouse_client_pool/__init__.py
clickhouse_client_pool/client.py
clickhouse_client_pool.egg-info/PKG-INFO
clickhouse_client_pool.egg-info/SOURCES.txt
clickhouse_client_pool.egg-info/dependency_links.txt
clickhouse_client_pool.egg-info/requires.txt
clickhouse_client_pool.egg-info/top_level.txt