Metadata-Version: 1.2
Name: clickhouse-client-pool
Version: 0.0.2
Summary: UNKNOWN
Home-page: https://github.com/lroolle/clickhouse-client-pool
Author: Eric Wang
Author-email: wrqatw@gmail.com
Maintainer: Eric Wang
Maintainer-email: wrqatw@gmail.com
License: MIT
Platform: UNKNOWN
Classifier: Development Status :: 4 - Beta
Classifier: Intended Audience :: Developers
Classifier: License :: OSI Approved :: MIT License
Classifier: Natural Language :: English
Classifier: Operating System :: OS Independent
Classifier: Programming Language :: Python :: 2.7
Classifier: Programming Language :: Python :: 3.6
